landable_parse_tool/__init__.py
landable_parse_tool/business.py
landable_parsing_tool-1.0.0.dist-info/METADATA
landable_parsing_tool-1.0.0.dist-info/WHEEL
landable_parsing_tool-1.0.0.dist-info/entry_points.txt
landable_parsing_tool-1.0.0.dist-info/top_level.txt
landable_parsing_tool-1.0.0.dist-info/RECORD
